useragent_rs/__init__.py
useragent_rs/base.py
useragent_rs/dataset.py
useragent_rs-0.1.5.dist-info/LICENSE
useragent_rs-0.1.5.dist-info/METADATA
useragent_rs-0.1.5.dist-info/WHEEL
useragent_rs-0.1.5.dist-info/entry_points.txt
useragent_rs-0.1.5.dist-info/top_level.txt
useragent_rs-0.1.5.dist-info/RECORD
