Metadata-Version: 2.1
Name: useragent-rs
Version: 0.1.5
Summary: User-Agent generator
Home-page: https://github.com/aloneinthedark/useragent_rs
Author: Rosario Sensale
Author-email: pcassistenzatecnica@gmail.com
Maintainer: Rosario Sensale
Maintainer-email: pcassistenzatecnica@gmail.com
License: MIT License
Download-URL: http://pypi.python.org/pypi/useragent_rs
Keywords: user agent browser navigator
Platform: UNKNOWN
Classifier: Programming Language :: Python
Classifier: Programming Language :: Python :: 2.7
Classifier: Programming Language :: Python :: 3.3
Classifier: Programming Language :: Python :: 3.4
Classifier: Programming Language :: Python :: 3.5
Classifier: Programming Language :: Python :: 3.6
Classifier: Programming Language :: Python :: Implementation :: CPython
Classifier: License :: OSI Approved :: MIT License
Classifier: Intended Audience :: Developers
Classifier: Operating System :: OS Independent
Classifier: Topic :: Software Development :: Libraries :: Python Modules
Classifier: Topic :: Internet :: WWW/HTTP
License-File: LICENSE
Requires-Dist: six
